graylogging/__init__.py
graylogging/__version__.py
graylogging/graylogging.py
graylogging/http_client.py
graylogging/tcp_client.py
graylogging/tools.py
graylogging/udp_client.py
graylogging-2.1.0.dist-info/METADATA
graylogging-2.1.0.dist-info/WHEEL
graylogging-2.1.0.dist-info/top_level.txt
graylogging-2.1.0.dist-info/RECORD
