Metadata-Version: 2.1
Name: graylogging
Version: 2.1.0
Summary: An extension to the builtin logging module that writes to a Graylog server instead of a flat file.
Home-page: https://github.com/ericrochow/graylogging
Author: Eric Rochow
Author-email: ericrochow+pypi@gmail.com
License: UNKNOWN
Platform: any
Classifier: Development Status :: 4 - Beta
Classifier: Intended Audience :: Developers
Classifier: Programming Language :: Python :: 3
Classifier: Programming Language :: Python :: 3.6
Classifier: Programming Language :: Python :: 3.7
Classifier: Programming Language :: Python :: 3.8
Classifier: Programming Language :: Python :: 3.9
Requires-Python: >=3.6
Requires-Dist: requests[security]
Provides-Extra: docs
Requires-Dist: Sphinx ; extra == 'docs'
Requires-Dist: SimpleHTTPServer ; extra == 'docs'
Requires-Dist: sphinx-rtd-theme ; extra == 'docs'
